topsis/__init__.py
topsis/topsis.py
topsis_csv_python3-1.0.1.dist-info/LICENSE
topsis_csv_python3-1.0.1.dist-info/METADATA
topsis_csv_python3-1.0.1.dist-info/WHEEL
topsis_csv_python3-1.0.1.dist-info/top_level.txt
topsis_csv_python3-1.0.1.dist-info/RECORD
