Metadata-Version: 2.1
Name: topsis-csv-python3
Version: 1.0.1
Summary: Implementation of Topsis
Home-page: https://github.com/NoOne03/topsis.git
Author: Prateek Kr Singh
Author-email: prateekkumarsingh3@gmail.com
License: UNKNOWN
Platform: UNKNOWN
Classifier: Programming Language :: Python :: 3
Classifier: License :: OSI Approved :: MIT License
Classifier: Operating System :: OS Independent
Requires-Python: >=3.6
